.gitignore
HISTORY.txt
MANIFEST.in
README.txt
setup.py
src/slc/__init__.py
src/slc.quickchangenote.egg-info/PKG-INFO
src/slc.quickchangenote.egg-info/SOURCES.txt
src/slc.quickchangenote.egg-info/dependency_links.txt
src/slc.quickchangenote.egg-info/entry_points.txt
src/slc.quickchangenote.egg-info/namespace_packages.txt
src/slc.quickchangenote.egg-info/not-zip-safe
src/slc.quickchangenote.egg-info/paster_plugins.txt
src/slc.quickchangenote.egg-info/requires.txt
src/slc.quickchangenote.egg-info/top_level.txt
src/slc/quickchangenote/__init__.py
src/slc/quickchangenote/configure.zcml
src/slc/quickchangenote/eventhandlers.py
src/slc/quickchangenote/interfaces.py
src/slc/quickchangenote/utils.py
src/slc/quickchangenote/browser/__init__.py
src/slc/quickchangenote/browser/configure.zcml
src/slc/quickchangenote/browser/edit.pt
src/slc/quickchangenote/browser/javascript.pt
src/slc/quickchangenote/browser/viewlets.py
src/slc/quickchangenote/browser/views.py
src/slc/quickchangenote/browser/resources/jquery.autocomplete.css
src/slc/quickchangenote/browser/resources/jquery.autocomplete.js
src/slc/quickchangenote/browser/resources/jquery.autocomplete.pack.js
src/slc/quickchangenote/profiles/default/browserlayer.xml
src/slc/quickchangenote/profiles/default/controlpanel.xml
src/slc/quickchangenote/profiles/default/cssregistry.xml
src/slc/quickchangenote/profiles/default/jsregistry.xml
src/slc/quickchangenote/profiles/default/metadata.xml
src/slc/quickchangenote/profiles/default/registry.xml