Metadata-Version: 1.0
Name: slc.quickchangenote
Version: 0.3
Summary: Provide an auto-complete Change Note field for CMFEditions
Home-page: https://github.com/syslabcom/slc.quickchangenote
Author: Izak Burger, Syslab.com GmbH
Author-email: isburger@gmail.com
License: GPL
Keywords: CMFEditions flexbox
Platform: UNKNOWN
Classifier: Programming Language :: Python
